setup.py
kleenex/__init__.py
kleenex/config.py
kleenex/db.py
kleenex/diff.py
kleenex/plugin.py
kleenex/tracer.py
kleenex/utils.py
kleenex.egg-info/PKG-INFO
kleenex.egg-info/SOURCES.txt
kleenex.egg-info/dependency_links.txt
kleenex.egg-info/entry_points.txt
kleenex.egg-info/not-zip-safe
kleenex.egg-info/requires.txt
kleenex.egg-info/top_level.txt
tests/config/__init__.py
tests/config/tests.py
tests/db/__init__.py
tests/db/tests.py